MANIFEST.in
README.rst
VERSION
requirements.txt
setup.py
patton_cli.egg-info/PKG-INFO
patton_cli.egg-info/SOURCES.txt
patton_cli.egg-info/dependency_links.txt
patton_cli.egg-info/entry_points.txt
patton_cli.egg-info/requires.txt
patton_cli.egg-info/top_level.txt
patton_client/__init__.py
patton_client/api_queires.py
patton_client/check_banners.py
patton_client/check_dependencies.py
patton_client/cli.py
patton_client/exceptions.py
patton_client/helpers.py
patton_client/model.py
patton_client/banners_services/__init__.py
patton_client/banners_services/nmap.py
patton_client/libraries_parsers/__init__.py
patton_client/libraries_parsers/alpine.py
patton_client/libraries_parsers/dpkg.py
patton_client/libraries_parsers/golang.py
patton_client/libraries_parsers/python.py
patton_client/libraries_parsers/simple.py