Metadata-Version: 1.1
Name: patton-cli
Version: 1.0.13
Summary: CLI for Patton-Server: The vulnerability knowledge store
Home-page: https://github.com/bbva/patton-cli
Author: BBVA Labs
Author-email: UNKNOWN
License: MIT
Platform: UNKNOWN
Classifier: Environment :: Console
Classifier: Intended Audience :: System Administrators
Classifier: Intended Audience :: Other Audience
Classifier: License :: OSI Approved :: BSD License
Classifier: Operating System :: MacOS
Classifier: Operating System :: Microsoft :: Windows
Classifier: Operating System :: POSIX
Classifier: Programming Language :: Python :: 3
